mczouz-2.1.0.data/purelib/MCMC/__init__.py
mczouz-2.1.0.data/purelib/MCMC/maxmumclique.cp39-win_amd64.pyd
mczouz-2.1.0.dist-info/LICENSE.txt
mczouz-2.1.0.dist-info/METADATA
mczouz-2.1.0.dist-info/WHEEL
mczouz-2.1.0.dist-info/top_level.txt
mczouz-2.1.0.dist-info/RECORD
