Metadata-Version: 2.1
Name: mczouz
Version: 2.1.0
Summary: Algotirhm to find maximalclique
Home-page: UNKNOWN
Author: UNKNOWN
Author-email: UNKNOWN
License: UNKNOWN
Platform: UNKNOWN
